exc_etr/aboutproject.py
exc_etr/etr.py
exc_etr/etr_line.py
exc_etr/utils.py
exc_etr-0.0.1.dist-info/LICENSE
exc_etr-0.0.1.dist-info/WHEEL
exc_etr-0.0.1.dist-info/METADATA
exc_etr-0.0.1.dist-info/RECORD
