Metadata-Version: 2.1
Name: exc-etr
Version: 0.0.1
Summary: 
License: GPLv3
Author: suizokukan
Author-email: suizokukan@orange.fr
Requires-Python: >=3.9,<4.0
Classifier: License :: Other/Proprietary License
Classifier: Programming Language :: Python :: 3
Classifier: Programming Language :: Python :: 3.10
Classifier: Programming Language :: Python :: 3.9
Requires-Dist: exc-motherclass (>=0.0.0,<0.0.1)
